dj_ratelimit/__init__.py
dj_ratelimit/src/__init__.py
dj_ratelimit/src/bucket.py
dj_ratelimit/src/redis_client.py
dj_ratelimit/tst/__init__.py
dj_ratelimit/tst/settings_default.py
dj_ratelimit/tst/test_ratelimit.py
dj_ratelimit-0.1.5.dist-info/LICENSE
dj_ratelimit-0.1.5.dist-info/METADATA
dj_ratelimit-0.1.5.dist-info/WHEEL
dj_ratelimit-0.1.5.dist-info/top_level.txt
dj_ratelimit-0.1.5.dist-info/RECORD
